niscope/__init__.py
niscope/niScopeTypes.py
niscope/ordered_symbols.py
pyniscope-0.4.0.dist-info/DESCRIPTION.rst
pyniscope-0.4.0.dist-info/METADATA
pyniscope-0.4.0.dist-info/RECORD
pyniscope-0.4.0.dist-info/WHEEL
pyniscope-0.4.0.dist-info/metadata.json
pyniscope-0.4.0.dist-info/top_level.txt
