Metadata-Version: 2.0
Name: pyniscope
Version: 0.4.0
Summary: Python wrapper for NI Oscilloscopes
Home-page: https://github.com/bernardokyotoku/pyniscope
Author: Bernardo Kyotoku, John Vishnefske
Author-email: jvdude.developer@mailnull.com
License: UNKNOWN
Platform: UNKNOWN
Classifier: Programming Language :: Python
Classifier: Development Status :: 4 - Beta
Classifier: License :: OSI Approved :: GNU General Public License v3 (GPLv3)
Classifier: Natural Language :: English
Classifier: Operating System :: Microsoft :: Windows
Classifier: Operating System :: Microsoft :: Windows :: Windows 7
Classifier: Operating System :: POSIX :: Linux
Classifier: Programming Language :: Python :: 3.6
Classifier: Programming Language :: Python :: 2.7
Classifier: Topic :: Scientific/Engineering
Classifier: Topic :: Software Development :: Libraries :: Python Modules
Classifier: Intended Audience :: Science/Research
Requires-Dist: numpy
